redxclient-0.2.4.dist-info/METADATA
redxclient-0.2.4.dist-info/WHEEL
redxclient/__init__.py
redxclient/schema/__init__.py
redxclient/schema/areas.py
redxclient/schema/parcel.py
redxclient/schema/pickup.py
redxclient-0.2.4.dist-info/RECORD
