Metadata-Version: 2.1
Name: RedXClient
Version: 0.2.4
Summary: A Python Client for RedX Courier Service
Home-page: https://gitlab.com/codesigntheory/redxclient
Author-Email: Utsob Roy <roy@co.design>
License: MPL-2.0
Project-URL: Homepage, https://gitlab.com/codesigntheory/redxclient
Requires-Python: >=3.8
Requires-Dist: pydantic>=2.6.4
Requires-Dist: requests>=2.31.0
